data_catalog/__init__.py
data_catalog/abc.py
data_catalog/collections.py
data_catalog/datasets.py
data_catalog/file_systems.py
data_catalog/taskgraph.py
data_catalog/utils.py
data_catalog/version.py
project_data_catalog-0.3.1.dist-info/METADATA
project_data_catalog-0.3.1.dist-info/WHEEL
project_data_catalog-0.3.1.dist-info/RECORD
