Metadata-Version: 2.1
Name: project-data-catalog
Version: 0.3.1
Summary: A catalog to define, create, store, and access datasets
Project-URL: Homepage, https://github.com/numerical-io/data_catalog
License-Expression: MIT
Requires-Python: >=3.7
Requires-Dist: dask>=0.2.0
Requires-Dist: pandas>=0.19
Requires-Dist: pytz>=2014
Requires-Dist: s3fs>=0.2.0
